argify/__init__.py
argify/argify.py
argify-0.0.6.dist-info/METADATA
argify-0.0.6.dist-info/WHEEL
argify-0.0.6.dist-info/top_level.txt
argify-0.0.6.dist-info/RECORD
