Metadata-Version: 2.1
Name: argify
Version: 0.0.6
Summary: Make your script args easier
Home-page: https://github.com/plaraje/
Author: Plaraje
Author-email: plaraje@proton.me
Classifier: Programming Language :: Python :: 3
Classifier: Programming Language :: Python :: 3.6
Classifier: Programming Language :: Python :: 3.7
Classifier: Programming Language :: Python :: 3.8
Classifier: Programming Language :: Python :: 3.9
Classifier: Programming Language :: Python :: 3.10
